{"data":[{"id":109085608,"readable":true,"title":"Perfecta","title_short":"Perfecta","link":"https:\/\/www.deezer.com\/track\/109085608","duration":225,"rank":605235,"explicit_lyrics":true,"explicit_content_lyrics":1,"explicit_content_cover":2,"preview":"https:\/\/cdns-preview-2.dzcdn.net\/stream\/c-25e040f38cdd5fabb424b5ae7e72b497-7.mp3","md5_image":"88d629d14280f83189dc5d48a640ea84","artist":{"id":4996,"name":"Miranda!","link":"https:\/\/www.deezer.com\/artist\/4996","picture":"https:\/\/api.deezer.com\/artist\/4996\/image","picture_small":"https:\/\/e-cdns-images.dzcdn.net\/images\/artist\/4e835792136fd35d7d442a79ec13e9fe\/56x56-000000-80-0-0.jpg","picture_medium":"https:\/\/e-cdns-images.dzcdn.net\/images\/artist\/4e835792136fd35d7d442a79ec13e9fe\/250x250-000000-80-0-0.jpg","picture_big":"https:\/\/e-cdns-images.dzcdn.net\/images\/artist\/4e835792136fd35d7d442a79ec13e9fe\/500x500-000000-80-0-0.jpg","picture_xl":"https:\/\/e-cdns-images.dzcdn.net\/images\/artist\/4e835792136fd35d7d442a79ec13e9fe\/1000x1000-000000-80-0-0.jpg","tracklist":"https:\/\/api.deezer.com\/artist\/4996\/top?limit=50","type":"artist"},"album":{"id":11366648,"title":"El Templo del Pop","cover":"https:\/\/api.deezer.com\/album\/11366648\/image","cover_small":"https:\/\/e-cdns-images.dzcdn.net\/images\/cover\/88d629d14280f83189dc5d48a640ea84\/56x56-000000-80-0-0.jpg","cover_medium":"https:\/\/e-cdns-images.dzcdn.net\/images\/cover\/88d629d14280f83189dc5d48a640ea84\/250x250-000000-80-0-0.jpg","cover_big":"https:\/\/e-cdns-images.dzcdn.net\/images\/cover\/88d629d14280f83189dc5d48a640ea84\/500x500-000000-80-0-0.jpg","cover_xl":"https:\/\/e-cdns-images.dzcdn.net\/images\/cover\/88d629d14280f83189dc5d48a640ea84\/1000x1000-000000-80-0-0.jpg","md5_image":"88d629d14280f83189dc5d48a640ea84","tracklist":"https:\/\/api.deezer.com\/album\/11366648\/tracks","type":"album"},"type":"track"},{"id":109085614,"readable":true,"title":"Don","title_short":"Don","link":"https:\/\/www.deezer.com\/track\/109085614","duration":183,"rank":588173,"explicit_lyrics":true,"explicit_content_lyrics":1,"explicit_content_cover":2,"preview":"https:\/\/cdns-preview-1.dzcdn.net\/stream\/c-1f773d6105ec817710a975dd9819258b-7.mp3","md5_image":"88d629d14280f83189dc5d48a640ea84","artist":{"id":4996,"name":"Miranda!","link":"https:\/\/www.deezer.com\/artist\/4996","picture":"https:\/\/api.deezer.com\/artist\/4996\/image","picture_small":"https:\/\/e-cdns-images.dzcdn.net\/images\/artist\/4e835792136fd35d7d442a79ec13e9fe\/56x56-000000-80-0-0.jpg","picture_medium":"https:\/\/e-cdns-images.dzcdn.net\/images\/artist\/4e835792136fd35d7d442a79ec13e9fe\/250x250-000000-80-0-0.jpg","picture_big":"https:\/\/e-cdns-images.dzcdn.net\/images\/artist\/4e835792136fd35d7d442a79ec13e9fe\/500x500-000000-80-0-0.jpg","picture_xl":"https:\/\/e-cdns-images.dzcdn.net\/images\/artist\/4e835792136fd35d7d442a79ec13e9fe\/1000x1000-000000-80-0-0.jpg","tracklist":"https:\/\/api.deezer.com\/artist\/4996\/top?limit=50","type":"artist"},"album":{"id":11366648,"title":"El Templo del Pop","cover":"https:\/\/api.deezer.com\/album\/11366648\/image","cover_small":"https:\/\/e-cdns-images.dzcdn.net\/images\/cover\/88d629d14280f83189dc5d48a640ea84\/56x56-000000-80-0-0.jpg","cover_medium":"https:\/\/e-cdns-images.dzcdn.net\/images\/cover\/88d629d14280f83189dc5d48a640ea84\/250x250-000000-80-0-0.jpg","cover_big":"https:\/\/e-cdns-images.dzcdn.net\/images\/cover\/88d629d14280f83189dc5d48a640ea84\/500x500-000000-80-0-0.jpg","cover_xl":"https:\/\/e-cdns-images.dzcdn.net\/images\/cover\/88d629d14280f83189dc5d48a640ea84\/1000x1000-000000-80-0-0.jpg","md5_image":"88d629d14280f83189dc5d48a640ea84","tracklist":"https:\/\/api.deezer.com\/album\/11366648\/tracks","type":"album"},"type":"track"},{"id":109383952,"readable":true,"title":"Tu Misterioso Alguien","title_short":"Tu Misterioso Alguien","link":"https:\/\/www.deezer.com\/track\/109383952","duration":244,"rank":504817,"explicit_lyrics":true,"explicit_content_lyrics":1,"explicit_content_cover":2,"preview":"https:\/\/cdns-preview-6.dzcdn.net\/stream\/c-6a229537d77377cfa68c39ecce5fc95a-7.mp3","md5_image":"d9b9fb4f9336acdceb807f0a736fdeb1","artist":{"id":4996,"name":"Miranda!","link":"https:\/\/www.deezer.com\/artist\/4996","picture":"https:\/\/api.deezer.com\/artist\/4996\/image","picture_small":"https:\/\/e-cdns-images.dzcdn.net\/images\/artist\/4e835792136fd35d7d442a79ec13e9fe\/56x56-000000-80-0-0.jpg","picture_medium":"https:\/\/e-cdns-images.dzcdn.net\/images\/artist\/4e835792136fd35d7d442a79ec13e9fe\/250x250-000000-80-0-0.jpg","picture_big":"https:\/\/e-cdns-images.dzcdn.net\/images\/artist\/4e835792136fd35d7d442a79ec13e9fe\/500x500-000000-80-0-0.jpg","picture_xl":"https:\/\/e-cdns-images.dzcdn.net\/images\/artist\/4e835792136fd35d7d442a79ec13e9fe\/1000x1000-000000-80-0-0.jpg","tracklist":"https:\/\/api.deezer.com\/artist\/4996\/top?limit=50","type":"artist"},"album":{"id":11396462,"title":"Miranda Es Imposible!","cover":"https:\/\/api.deezer.com\/album\/11396462\/image","cover_small":"https:\/\/e-cdns-images.dzcdn.net\/images\/cover\/d9b9fb4f9336acdceb807f0a736fdeb1\/56x56-000000-80-0-0.jpg","cover_medium":"https:\/\/e-cdns-images.dzcdn.net\/images\/cover\/d9b9fb4f9336acdceb807f0a736fdeb1\/250x250-000000-80-0-0.jpg","cover_big":"https:\/\/e-cdns-images.dzcdn.net\/images\/cover\/d9b9fb4f9336acdceb807f0a736fdeb1\/500x500-000000-80-0-0.jpg","cover_xl":"https:\/\/e-cdns-images.dzcdn.net\/images\/cover\/d9b9fb4f9336acdceb807f0a736fdeb1\/1000x1000-000000-80-0-0.jpg","md5_image":"d9b9fb4f9336acdceb807f0a736fdeb1","tracklist":"https:\/\/api.deezer.com\/album\/11396462\/tracks","type":"album"},"type":"track"},{"id":109383942,"readable":true,"title":"Ment\u00eda","title_short":"Ment\u00eda","link":"https:\/\/www.deezer.com\/track\/109383942","duration":215,"rank":424019,"explicit_lyrics":true,"explicit_content_lyrics":1,"explicit_content_cover":2,"preview":"https:\/\/cdns-preview-9.dzcdn.net\/stream\/c-959ac2686e6717172a6292b7eb6ef02a-7.mp3","md5_image":"d9b9fb4f9336acdceb807f0a736fdeb1","artist":{"id":4996,"name":"Miranda!","link":"https:\/\/www.deezer.com\/artist\/4996","picture":"https:\/\/api.deezer.com\/artist\/4996\/image","picture_small":"https:\/\/e-cdns-images.dzcdn.net\/images\/artist\/4e835792136fd35d7d442a79ec13e9fe\/56x56-000000-80-0-0.jpg","picture_medium":"https:\/\/e-cdns-images.dzcdn.net\/images\/artist\/4e835792136fd35d7d442a79ec13e9fe\/250x250-000000-80-0-0.jpg","picture_big":"https:\/\/e-cdns-images.dzcdn.net\/images\/artist\/4e835792136fd35d7d442a79ec13e9fe\/500x500-000000-80-0-0.jpg","picture_xl":"https:\/\/e-cdns-images.dzcdn.net\/images\/artist\/4e835792136fd35d7d442a79ec13e9fe\/1000x1000-000000-80-0-0.jpg","tracklist":"https:\/\/api.deezer.com\/artist\/4996\/top?limit=50","type":"artist"},"album":{"id":11396462,"title":"Miranda Es Imposible!","cover":"https:\/\/api.deezer.com\/album\/11396462\/image","cover_small":"https:\/\/e-cdns-images.dzcdn.net\/images\/cover\/d9b9fb4f9336acdceb807f0a736fdeb1\/56x56-000000-80-0-0.jpg","cover_medium":"https:\/\/e-cdns-images.dzcdn.net\/images\/cover\/d9b9fb4f9336acdceb807f0a736fdeb1\/250x250-000000-80-0-0.jpg","cover_big":"https:\/\/e-cdns-images.dzcdn.net\/images\/cover\/d9b9fb4f9336acdceb807f0a736fdeb1\/500x500-000000-80-0-0.jpg","cover_xl":"https:\/\/e-cdns-images.dzcdn.net\/images\/cover\/d9b9fb4f9336acdceb807f0a736fdeb1\/1000x1000-000000-80-0-0.jpg","md5_image":"d9b9fb4f9336acdceb807f0a736fdeb1","tracklist":"https:\/\/api.deezer.com\/album\/11396462\/tracks","type":"album"},"type":"track"},{"id":108383094,"readable":true,"title":"Prisionero","title_short":"Prisionero","link":"https:\/\/www.deezer.com\/track\/108383094","duration":207,"rank":405739,"explicit_lyrics":false,"explicit_content_lyrics":0,"explicit_content_cover":2,"preview":"https:\/\/cdns-preview-a.dzcdn.net\/stream\/c-aa3b85f8e8cd967cf5dc924525e398e3-7.mp3","md5_image":"69dfcf77213edd3627eaf31ebc3a40ce","artist":{"id":4996,"name":"Miranda!","link":"https:\/\/www.deezer.com\/artist\/4996","picture":"https:\/\/api.deezer.com\/artist\/4996\/image","picture_small":"https:\/\/e-cdns-images.dzcdn.net\/images\/artist\/4e835792136fd35d7d442a79ec13e9fe\/56x56-000000-80-0-0.jpg","picture_medium":"https:\/\/e-cdns-images.dzcdn.net\/images\/artist\/4e835792136fd35d7d442a79ec13e9fe\/250x250-000000-80-0-0.jpg","picture_big":"https:\/\/e-cdns-images.dzcdn.net\/images\/artist\/4e835792136fd35d7d442a79ec13e9fe\/500x500-000000-80-0-0.jpg","picture_xl":"https:\/\/e-cdns-images.dzcdn.net\/images\/artist\/4e835792136fd35d7d442a79ec13e9fe\/1000x1000-000000-80-0-0.jpg","tracklist":"https:\/\/api.deezer.com\/artist\/4996\/top?limit=50","type":"artist"},"album":{"id":11302102,"title":"El Disco de Tu Coraz\u00f3n","cover":"https:\/\/api.deezer.com\/album\/11302102\/image","cover_small":"https:\/\/e-cdns-images.dzcdn.net\/images\/cover\/69dfcf77213edd3627eaf31ebc3a40ce\/56x56-000000-80-0-0.jpg","cover_medium":"https:\/\/e-cdns-images.dzcdn.net\/images\/cover\/69dfcf77213edd3627eaf31ebc3a40ce\/250x250-000000-80-0-0.jpg","cover_big":"https:\/\/e-cdns-images.dzcdn.net\/images\/cover\/69dfcf77213edd3627eaf31ebc3a40ce\/500x500-000000-80-0-0.jpg","cover_xl":"https:\/\/e-cdns-images.dzcdn.net\/images\/cover\/69dfcf77213edd3627eaf31ebc3a40ce\/1000x1000-000000-80-0-0.jpg","md5_image":"69dfcf77213edd3627eaf31ebc3a40ce","tracklist":"https:\/\/api.deezer.com\/album\/11302102\/tracks","type":"album"},"type":"track"},{"id":108383100,"readable":true,"title":"Enamorada","title_short":"Enamorada","link":"https:\/\/www.deezer.com\/track\/108383100","duration":193,"rank":416973,"explicit_lyrics":true,"explicit_content_lyrics":1,"explicit_content_cover":2,"preview":"https:\/\/cdns-preview-6.dzcdn.net\/stream\/c-65fc013910f3eaf75fb613afe03ae08e-7.mp3","md5_image":"69dfcf77213edd3627eaf31ebc3a40ce","artist":{"id":4996,"name":"Miranda!","link":"https:\/\/www.deezer.com\/artist\/4996","picture":"https:\/\/api.deezer.com\/artist\/4996\/image","picture_small":"https:\/\/e-cdns-images.dzcdn.net\/images\/artist\/4e835792136fd35d7d442a79ec13e9fe\/56x56-000000-80-0-0.jpg","picture_medium":"https:\/\/e-cdns-images.dzcdn.net\/images\/artist\/4e835792136fd35d7d442a79ec13e9fe\/250x250-000000-80-0-0.jpg","picture_big":"https:\/\/e-cdns-images.dzcdn.net\/images\/artist\/4e835792136fd35d7d442a79ec13e9fe\/500x500-000000-80-0-0.jpg","picture_xl":"https:\/\/e-cdns-images.dzcdn.net\/images\/artist\/4e835792136fd35d7d442a79ec13e9fe\/1000x1000-000000-80-0-0.jpg","tracklist":"https:\/\/api.deezer.com\/artist\/4996\/top?limit=50","type":"artist"},"album":{"id":11302102,"title":"El Disco de Tu Coraz\u00f3n","cover":"https:\/\/api.deezer.com\/album\/11302102\/image","cover_small":"https:\/\/e-cdns-images.dzcdn.net\/images\/cover\/69dfcf77213edd3627eaf31ebc3a40ce\/56x56-000000-80-0-0.jpg","cover_medium":"https:\/\/e-cdns-images.dzcdn.net\/images\/cover\/69dfcf77213edd3627eaf31ebc3a40ce\/250x250-000000-80-0-0.jpg","cover_big":"https:\/\/e-cdns-images.dzcdn.net\/images\/cover\/69dfcf77213edd3627eaf31ebc3a40ce\/500x500-000000-80-0-0.jpg","cover_xl":"https:\/\/e-cdns-images.dzcdn.net\/images\/cover\/69dfcf77213edd3627eaf31ebc3a40ce\/1000x1000-000000-80-0-0.jpg","md5_image":"69dfcf77213edd3627eaf31ebc3a40ce","tracklist":"https:\/\/api.deezer.com\/album\/11302102\/tracks","type":"album"},"type":"track"},{"id":108383098,"readable":true,"title":"Perfecta","title_short":"Perfecta","link":"https:\/\/www.deezer.com\/track\/108383098","duration":225,"rank":442108,"explicit_lyrics":true,"explicit_content_lyrics":1,"explicit_content_cover":2,"preview":"https:\/\/cdns-preview-9.dzcdn.net\/stream\/c-9e2b93fa0a1d9f24e93091a59e1aaaca-7.mp3","md5_image":"69dfcf77213edd3627eaf31ebc3a40ce","artist":{"id":4996,"name":"Miranda!","link":"https:\/\/www.deezer.com\/artist\/4996","picture":"https:\/\/api.deezer.com\/artist\/4996\/image","picture_small":"https:\/\/e-cdns-images.dzcdn.net\/images\/artist\/4e835792136fd35d7d442a79ec13e9fe\/56x56-000000-80-0-0.jpg","picture_medium":"https:\/\/e-cdns-images.dzcdn.net\/images\/artist\/4e835792136fd35d7d442a79ec13e9fe\/250x250-000000-80-0-0.jpg","picture_big":"https:\/\/e-cdns-images.dzcdn.net\/images\/artist\/4e835792136fd35d7d442a79ec13e9fe\/500x500-000000-80-0-0.jpg","picture_xl":"https:\/\/e-cdns-images.dzcdn.net\/images\/artist\/4e835792136fd35d7d442a79ec13e9fe\/1000x1000-000000-80-0-0.jpg","tracklist":"https:\/\/api.deezer.com\/artist\/4996\/top?limit=50","type":"artist"},"album":{"id":11302102,"title":"El Disco de Tu Coraz\u00f3n","cover":"https:\/\/api.deezer.com\/album\/11302102\/image","cover_small":"https:\/\/e-cdns-images.dzcdn.net\/images\/cover\/69dfcf77213edd3627eaf31ebc3a40ce\/56x56-000000-80-0-0.jpg","cover_medium":"https:\/\/e-cdns-images.dzcdn.net\/images\/cover\/69dfcf77213edd3627eaf31ebc3a40ce\/250x250-000000-80-0-0.jpg","cover_big":"https:\/\/e-cdns-images.dzcdn.net\/images\/cover\/69dfcf77213edd3627eaf31ebc3a40ce\/500x500-000000-80-0-0.jpg","cover_xl":"https:\/\/e-cdns-images.dzcdn.net\/images\/cover\/69dfcf77213edd3627eaf31ebc3a40ce\/1000x1000-000000-80-0-0.jpg","md5_image":"69dfcf77213edd3627eaf31ebc3a40ce","tracklist":"https:\/\/api.deezer.com\/album\/11302102\/tracks","type":"album"},"type":"track"},{"id":109306284,"readable":true,"title":"Traici\u00f3n","title_short":"Traici\u00f3n","link":"https:\/\/www.deezer.com\/track\/109306284","duration":182,"rank":417646,"explicit_lyrics":false,"explicit_content_lyrics":0,"explicit_content_cover":2,"preview":"https:\/\/cdns-preview-5.dzcdn.net\/stream\/c-54b14f8f3724ef5524d869918f96728a-8.mp3","md5_image":"efba4098a633a30bc8af0eeda0ac154d","artist":{"id":4996,"name":"Miranda!","link":"https:\/\/www.deezer.com\/artist\/4996","picture":"https:\/\/api.deezer.com\/artist\/4996\/image","picture_small":"https:\/\/e-cdns-images.dzcdn.net\/images\/artist\/4e835792136fd35d7d442a79ec13e9fe\/56x56-000000-80-0-0.jpg","picture_medium":"https:\/\/e-cdns-images.dzcdn.net\/images\/artist\/4e835792136fd35d7d442a79ec13e9fe\/250x250-000000-80-0-0.jpg","picture_big":"https:\/\/e-cdns-images.dzcdn.net\/images\/artist\/4e835792136fd35d7d442a79ec13e9fe\/500x500-000000-80-0-0.jpg","picture_xl":"https:\/\/e-cdns-images.dzcdn.net\/images\/artist\/4e835792136fd35d7d442a79ec13e9fe\/1000x1000-000000-80-0-0.jpg","tracklist":"https:\/\/api.deezer.com\/artist\/4996\/top?limit=50","type":"artist"},"album":{"id":11389434,"title":"Sin Restricciones","cover":"https:\/\/api.deezer.com\/album\/11389434\/image","cover_small":"https:\/\/e-cdns-images.dzcdn.net\/images\/cover\/efba4098a633a30bc8af0eeda0ac154d\/56x56-000000-80-0-0.jpg","cover_medium":"https:\/\/e-cdns-images.dzcdn.net\/images\/cover\/efba4098a633a30bc8af0eeda0ac154d\/250x250-000000-80-0-0.jpg","cover_big":"https:\/\/e-cdns-images.dzcdn.net\/images\/cover\/efba4098a633a30bc8af0eeda0ac154d\/500x500-000000-80-0-0.jpg","cover_xl":"https:\/\/e-cdns-images.dzcdn.net\/images\/cover\/efba4098a633a30bc8af0eeda0ac154d\/1000x1000-000000-80-0-0.jpg","md5_image":"efba4098a633a30bc8af0eeda0ac154d","tracklist":"https:\/\/api.deezer.com\/album\/11389434\/tracks","type":"album"},"type":"track"},{"id":1985158157,"readable":true,"title":"Don","title_short":"Don","title_version":"","link":"https:\/\/www.deezer.com\/track\/1985158157","duration":189,"rank":404020,"explicit_lyrics":false,"explicit_content_lyrics":0,"explicit_content_cover":2,"preview":"https:\/\/cdns-preview-2.dzcdn.net\/stream\/c-2c75f8893f5fb90870beb20fe7ee8615-2.mp3","md5_image":"98ffd765e65ec529ef2b9045081a62e6","artist":{"id":4996,"name":"Miranda!","link":"https:\/\/www.deezer.com\/artist\/4996","picture":"https:\/\/api.deezer.com\/artist\/4996\/image","picture_small":"https:\/\/e-cdns-images.dzcdn.net\/images\/artist\/4e835792136fd35d7d442a79ec13e9fe\/56x56-000000-80-0-0.jpg","picture_medium":"https:\/\/e-cdns-images.dzcdn.net\/images\/artist\/4e835792136fd35d7d442a79ec13e9fe\/250x250-000000-80-0-0.jpg","picture_big":"https:\/\/e-cdns-images.dzcdn.net\/images\/artist\/4e835792136fd35d7d442a79ec13e9fe\/500x500-000000-80-0-0.jpg","picture_xl":"https:\/\/e-cdns-images.dzcdn.net\/images\/artist\/4e835792136fd35d7d442a79ec13e9fe\/1000x1000-000000-80-0-0.jpg","tracklist":"https:\/\/api.deezer.com\/artist\/4996\/top?limit=50","type":"artist"},"album":{"id":370117737,"title":"Don","cover":"https:\/\/api.deezer.com\/album\/370117737\/image","cover_small":"https:\/\/e-cdns-images.dzcdn.net\/images\/cover\/98ffd765e65ec529ef2b9045081a62e6\/56x56-000000-80-0-0.jpg","cover_medium":"https:\/\/e-cdns-images.dzcdn.net\/images\/cover\/98ffd765e65ec529ef2b9045081a62e6\/250x250-000000-80-0-0.jpg","cover_big":"https:\/\/e-cdns-images.dzcdn.net\/images\/cover\/98ffd765e65ec529ef2b9045081a62e6\/500x500-000000-80-0-0.jpg","cover_xl":"https:\/\/e-cdns-images.dzcdn.net\/images\/cover\/98ffd765e65ec529ef2b9045081a62e6\/1000x1000-000000-80-0-0.jpg","md5_image":"98ffd765e65ec529ef2b9045081a62e6","tracklist":"https:\/\/api.deezer.com\/album\/370117737\/tracks","type":"album"},"type":"track"},{"id":692200712,"readable":true,"title":"Me Gustas Tanto","title_short":"Me Gustas Tanto","title_version":"","link":"https:\/\/www.deezer.com\/track\/692200712","duration":219,"rank":362169,"explicit_lyrics":false,"explicit_content_lyrics":0,"explicit_content_cover":2,"preview":"https:\/\/cdns-preview-4.dzcdn.net\/stream\/c-4dea7a1d1ace6ff79d789b7149dd20f3-3.mp3","md5_image":"3a8be8fa077a0702bebe3776c247b0c2","artist":{"id":4996,"name":"Miranda!","link":"https:\/\/www.deezer.com\/artist\/4996","picture":"https:\/\/api.deezer.com\/artist\/4996\/image","picture_small":"https:\/\/e-cdns-images.dzcdn.net\/images\/artist\/4e835792136fd35d7d442a79ec13e9fe\/56x56-000000-80-0-0.jpg","picture_medium":"https:\/\/e-cdns-images.dzcdn.net\/images\/artist\/4e835792136fd35d7d442a79ec13e9fe\/250x250-000000-80-0-0.jpg","picture_big":"https:\/\/e-cdns-images.dzcdn.net\/images\/artist\/4e835792136fd35d7d442a79ec13e9fe\/500x500-000000-80-0-0.jpg","picture_xl":"https:\/\/e-cdns-images.dzcdn.net\/images\/artist\/4e835792136fd35d7d442a79ec13e9fe\/1000x1000-000000-80-0-0.jpg","tracklist":"https:\/\/api.deezer.com\/artist\/4996\/top?limit=50","type":"artist"},"album":{"id":99475272,"title":"Me Gustas Tanto","cover":"https:\/\/api.deezer.com\/album\/99475272\/image","cover_small":"https:\/\/e-cdns-images.dzcdn.net\/images\/cover\/3a8be8fa077a0702bebe3776c247b0c2\/56x56-000000-80-0-0.jpg","cover_medium":"https:\/\/e-cdns-images.dzcdn.net\/images\/cover\/3a8be8fa077a0702bebe3776c247b0c2\/250x250-000000-80-0-0.jpg","cover_big":"https:\/\/e-cdns-images.dzcdn.net\/images\/cover\/3a8be8fa077a0702bebe3776c247b0c2\/500x500-000000-80-0-0.jpg","cover_xl":"https:\/\/e-cdns-images.dzcdn.net\/images\/cover\/3a8be8fa077a0702bebe3776c247b0c2\/1000x1000-000000-80-0-0.jpg","md5_image":"3a8be8fa077a0702bebe3776c247b0c2","tracklist":"https:\/\/api.deezer.com\/album\/99475272\/tracks","type":"album"},"type":"track"},{"id":108383096,"readable":true,"title":"Hola","title_short":"Hola","link":"https:\/\/www.deezer.com\/track\/108383096","duration":185,"rank":425318,"explicit_lyrics":true,"explicit_content_lyrics":1,"explicit_content_cover":2,"preview":"https:\/\/cdns-preview-4.dzcdn.net\/stream\/c-4784bb9faec0b5abca7130d4bbba05f0-8.mp3","md5_image":"69dfcf77213edd3627eaf31ebc3a40ce","artist":{"id":4996,"name":"Miranda!","link":"https:\/\/www.deezer.com\/artist\/4996","picture":"https:\/\/api.deezer.com\/artist\/4996\/image","picture_small":"https:\/\/e-cdns-images.dzcdn.net\/images\/artist\/4e835792136fd35d7d442a79ec13e9fe\/56x56-000000-80-0-0.jpg","picture_medium":"https:\/\/e-cdns-images.dzcdn.net\/images\/artist\/4e835792136fd35d7d442a79ec13e9fe\/250x250-000000-80-0-0.jpg","picture_big":"https:\/\/e-cdns-images.dzcdn.net\/images\/artist\/4e835792136fd35d7d442a79ec13e9fe\/500x500-000000-80-0-0.jpg","picture_xl":"https:\/\/e-cdns-images.dzcdn.net\/images\/artist\/4e835792136fd35d7d442a79ec13e9fe\/1000x1000-000000-80-0-0.jpg","tracklist":"https:\/\/api.deezer.com\/artist\/4996\/top?limit=50","type":"artist"},"album":{"id":11302102,"title":"El Disco de Tu Coraz\u00f3n","cover":"https:\/\/api.deezer.com\/album\/11302102\/image","cover_small":"https:\/\/e-cdns-images.dzcdn.net\/images\/cover\/69dfcf77213edd3627eaf31ebc3a40ce\/56x56-000000-80-0-0.jpg","cover_medium":"https:\/\/e-cdns-images.dzcdn.net\/images\/cover\/69dfcf77213edd3627eaf31ebc3a40ce\/250x250-000000-80-0-0.jpg","cover_big":"https:\/\/e-cdns-images.dzcdn.net\/images\/cover\/69dfcf77213edd3627eaf31ebc3a40ce\/500x500-000000-80-0-0.jpg","cover_xl":"https:\/\/e-cdns-images.dzcdn.net\/images\/cover\/69dfcf77213edd3627eaf31ebc3a40ce\/1000x1000-000000-80-0-0.jpg","md5_image":"69dfcf77213edd3627eaf31ebc3a40ce","tracklist":"https:\/\/api.deezer.com\/album\/11302102\/tracks","type":"album"},"type":"track"},{"id":116946434,"readable":true,"title":"Ya Lo Sab\u00eda","title_short":"Ya Lo Sab\u00eda","link":"https:\/\/www.deezer.com\/track\/116946434","duration":178,"rank":388673,"explicit_lyrics":false,"explicit_content_lyrics":0,"explicit_content_cover":2,"preview":"https:\/\/cdns-preview-3.dzcdn.net\/stream\/c-306978bb98f6fed9256c4ae3d434ec7e-4.mp3","md5_image":"5b1d35ef7b1721f0478561ed85ba449b","artist":{"id":4996,"name":"Miranda!","link":"https:\/\/www.deezer.com\/artist\/4996","picture":"https:\/\/api.deezer.com\/artist\/4996\/image","picture_small":"https:\/\/e-cdns-images.dzcdn.net\/images\/artist\/4e835792136fd35d7d442a79ec13e9fe\/56x56-000000-80-0-0.jpg","picture_medium":"https:\/\/e-cdns-images.dzcdn.net\/images\/artist\/4e835792136fd35d7d442a79ec13e9fe\/250x250-000000-80-0-0.jpg","picture_big":"https:\/\/e-cdns-images.dzcdn.net\/images\/artist\/4e835792136fd35d7d442a79ec13e9fe\/500x500-000000-80-0-0.jpg","picture_xl":"https:\/\/e-cdns-images.dzcdn.net\/images\/artist\/4e835792136fd35d7d442a79ec13e9fe\/1000x1000-000000-80-0-0.jpg","tracklist":"https:\/\/api.deezer.com\/artist\/4996\/top?limit=50","type":"artist"},"album":{"id":12118506,"title":"Magistral","cover":"https:\/\/api.deezer.com\/album\/12118506\/image","cover_small":"https:\/\/e-cdns-images.dzcdn.net\/images\/cover\/5b1d35ef7b1721f0478561ed85ba449b\/56x56-000000-80-0-0.jpg","cover_medium":"https:\/\/e-cdns-images.dzcdn.net\/images\/cover\/5b1d35ef7b1721f0478561ed85ba449b\/250x250-000000-80-0-0.jpg","cover_big":"https:\/\/e-cdns-images.dzcdn.net\/images\/cover\/5b1d35ef7b1721f0478561ed85ba449b\/500x500-000000-80-0-0.jpg","cover_xl":"https:\/\/e-cdns-images.dzcdn.net\/images\/cover\/5b1d35ef7b1721f0478561ed85ba449b\/1000x1000-000000-80-0-0.jpg","md5_image":"5b1d35ef7b1721f0478561ed85ba449b","tracklist":"https:\/\/api.deezer.com\/album\/12118506\/tracks","type":"album"},"type":"track"},{"id":109085616,"readable":true,"title":"Yo Te Dir\u00e9","title_short":"Yo Te Dir\u00e9","link":"https:\/\/www.deezer.com\/track\/109085616","duration":206,"rank":419319,"explicit_lyrics":true,"explicit_content_lyrics":1,"explicit_content_cover":2,"preview":"https:\/\/cdns-preview-3.dzcdn.net\/stream\/c-3bd27e748ce55f2bd57023c8a7ae9699-8.mp3","md5_image":"88d629d14280f83189dc5d48a640ea84","artist":{"id":4996,"name":"Miranda!","link":"https:\/\/www.deezer.com\/artist\/4996","picture":"https:\/\/api.deezer.com\/artist\/4996\/image","picture_small":"https:\/\/e-cdns-images.dzcdn.net\/images\/artist\/4e835792136fd35d7d442a79ec13e9fe\/56x56-000000-80-0-0.jpg","picture_medium":"https:\/\/e-cdns-images.dzcdn.net\/images\/artist\/4e835792136fd35d7d442a79ec13e9fe\/250x250-000000-80-0-0.jpg","picture_big":"https:\/\/e-cdns-images.dzcdn.net\/images\/artist\/4e835792136fd35d7d442a79ec13e9fe\/500x500-000000-80-0-0.jpg","picture_xl":"https:\/\/e-cdns-images.dzcdn.net\/images\/artist\/4e835792136fd35d7d442a79ec13e9fe\/1000x1000-000000-80-0-0.jpg","tracklist":"https:\/\/api.deezer.com\/artist\/4996\/top?limit=50","type":"artist"},"album":{"id":11366648,"title":"El Templo del Pop","cover":"https:\/\/api.deezer.com\/album\/11366648\/image","cover_small":"https:\/\/e-cdns-images.dzcdn.net\/images\/cover\/88d629d14280f83189dc5d48a640ea84\/56x56-000000-80-0-0.jpg","cover_medium":"https:\/\/e-cdns-images.dzcdn.net\/images\/cover\/88d629d14280f83189dc5d48a640ea84\/250x250-000000-80-0-0.jpg","cover_big":"https:\/\/e-cdns-images.dzcdn.net\/images\/cover\/88d629d14280f83189dc5d48a640ea84\/500x500-000000-80-0-0.jpg","cover_xl":"https:\/\/e-cdns-images.dzcdn.net\/images\/cover\/88d629d14280f83189dc5d48a640ea84\/1000x1000-000000-80-0-0.jpg","md5_image":"88d629d14280f83189dc5d48a640ea84","tracklist":"https:\/\/api.deezer.com\/album\/11366648\/tracks","type":"album"},"type":"track"},{"id":109306264,"readable":true,"title":"Yo Te Dir\u00e9","title_short":"Yo Te Dir\u00e9","link":"https:\/\/www.deezer.com\/track\/109306264","duration":205,"rank":327573,"explicit_lyrics":false,"explicit_content_lyrics":0,"explicit_content_cover":2,"preview":"https:\/\/cdns-preview-d.dzcdn.net\/stream\/c-db3197dafa3be4a2ff85954b8c3fdfea-8.mp3","md5_image":"efba4098a633a30bc8af0eeda0ac154d","artist":{"id":4996,"name":"Miranda!","link":"https:\/\/www.deezer.com\/artist\/4996","picture":"https:\/\/api.deezer.com\/artist\/4996\/image","picture_small":"https:\/\/e-cdns-images.dzcdn.net\/images\/artist\/4e835792136fd35d7d442a79ec13e9fe\/56x56-000000-80-0-0.jpg","picture_medium":"https:\/\/e-cdns-images.dzcdn.net\/images\/artist\/4e835792136fd35d7d442a79ec13e9fe\/250x250-000000-80-0-0.jpg","picture_big":"https:\/\/e-cdns-images.dzcdn.net\/images\/artist\/4e835792136fd35d7d442a79ec13e9fe\/500x500-000000-80-0-0.jpg","picture_xl":"https:\/\/e-cdns-images.dzcdn.net\/images\/artist\/4e835792136fd35d7d442a79ec13e9fe\/1000x1000-000000-80-0-0.jpg","tracklist":"https:\/\/api.deezer.com\/artist\/4996\/top?limit=50","type":"artist"},"album":{"id":11389434,"title":"Sin Restricciones","cover":"https:\/\/api.deezer.com\/album\/11389434\/image","cover_small":"https:\/\/e-cdns-images.dzcdn.net\/images\/cover\/efba4098a633a30bc8af0eeda0ac154d\/56x56-000000-80-0-0.jpg","cover_medium":"https:\/\/e-cdns-images.dzcdn.net\/images\/cover\/efba4098a633a30bc8af0eeda0ac154d\/250x250-000000-80-0-0.jpg","cover_big":"https:\/\/e-cdns-images.dzcdn.net\/images\/cover\/efba4098a633a30bc8af0eeda0ac154d\/500x500-000000-80-0-0.jpg","cover_xl":"https:\/\/e-cdns-images.dzcdn.net\/images\/cover\/efba4098a633a30bc8af0eeda0ac154d\/1000x1000-000000-80-0-0.jpg","md5_image":"efba4098a633a30bc8af0eeda0ac154d","tracklist":"https:\/\/api.deezer.com\/album\/11389434\/tracks","type":"album"},"type":"track"},{"id":109085628,"readable":true,"title":"El Profe","title_short":"El Profe","link":"https:\/\/www.deezer.com\/track\/109085628","duration":176,"rank":275299,"explicit_lyrics":true,"explicit_content_lyrics":1,"explicit_content_cover":2,"preview":"https:\/\/cdns-preview-3.dzcdn.net\/stream\/c-3ca6979d01fff25f9a1a73c82994efb6-8.mp3","md5_image":"88d629d14280f83189dc5d48a640ea84","artist":{"id":4996,"name":"Miranda!","link":"https:\/\/www.deezer.com\/artist\/4996","picture":"https:\/\/api.deezer.com\/artist\/4996\/image","picture_small":"https:\/\/e-cdns-images.dzcdn.net\/images\/artist\/4e835792136fd35d7d442a79ec13e9fe\/56x56-000000-80-0-0.jpg","picture_medium":"https:\/\/e-cdns-images.dzcdn.net\/images\/artist\/4e835792136fd35d7d442a79ec13e9fe\/250x250-000000-80-0-0.jpg","picture_big":"https:\/\/e-cdns-images.dzcdn.net\/images\/artist\/4e835792136fd35d7d442a79ec13e9fe\/500x500-000000-80-0-0.jpg","picture_xl":"https:\/\/e-cdns-images.dzcdn.net\/images\/artist\/4e835792136fd35d7d442a79ec13e9fe\/1000x1000-000000-80-0-0.jpg","tracklist":"https:\/\/api.deezer.com\/artist\/4996\/top?limit=50","type":"artist"},"album":{"id":11366648,"title":"El Templo del Pop","cover":"https:\/\/api.deezer.com\/album\/11366648\/image","cover_small":"https:\/\/e-cdns-images.dzcdn.net\/images\/cover\/88d629d14280f83189dc5d48a640ea84\/56x56-000000-80-0-0.jpg","cover_medium":"https:\/\/e-cdns-images.dzcdn.net\/images\/cover\/88d629d14280f83189dc5d48a640ea84\/250x250-000000-80-0-0.jpg","cover_big":"https:\/\/e-cdns-images.dzcdn.net\/images\/cover\/88d629d14280f83189dc5d48a640ea84\/500x500-000000-80-0-0.jpg","cover_xl":"https:\/\/e-cdns-images.dzcdn.net\/images\/cover\/88d629d14280f83189dc5d48a640ea84\/1000x1000-000000-80-0-0.jpg","md5_image":"88d629d14280f83189dc5d48a640ea84","tracklist":"https:\/\/api.deezer.com\/album\/11366648\/tracks","type":"album"},"type":"track"},{"id":108828804,"readable":true,"title":"Extra\u00f1o","title_short":"Extra\u00f1o","title_version":"","link":"https:\/\/www.deezer.com\/track\/108828804","duration":236,"rank":321974,"explicit_lyrics":false,"explicit_content_lyrics":0,"explicit_content_cover":2,"preview":"https:\/\/cdns-preview-e.dzcdn.net\/stream\/c-ed4d51cafb717ca573b322fc426183ee-5.mp3","md5_image":"2c420eb8b02e64ecb3f4cbaf8d340774","artist":{"id":4996,"name":"Miranda!","link":"https:\/\/www.deezer.com\/artist\/4996","picture":"https:\/\/api.deezer.com\/artist\/4996\/image","picture_small":"https:\/\/e-cdns-images.dzcdn.net\/images\/artist\/4e835792136fd35d7d442a79ec13e9fe\/56x56-000000-80-0-0.jpg","picture_medium":"https:\/\/e-cdns-images.dzcdn.net\/images\/artist\/4e835792136fd35d7d442a79ec13e9fe\/250x250-000000-80-0-0.jpg","picture_big":"https:\/\/e-cdns-images.dzcdn.net\/images\/artist\/4e835792136fd35d7d442a79ec13e9fe\/500x500-000000-80-0-0.jpg","picture_xl":"https:\/\/e-cdns-images.dzcdn.net\/images\/artist\/4e835792136fd35d7d442a79ec13e9fe\/1000x1000-000000-80-0-0.jpg","tracklist":"https:\/\/api.deezer.com\/artist\/4996\/top?limit=50","type":"artist"},"album":{"id":11344934,"title":"Safari","cover":"https:\/\/api.deezer.com\/album\/11344934\/image","cover_small":"https:\/\/e-cdns-images.dzcdn.net\/images\/cover\/2c420eb8b02e64ecb3f4cbaf8d340774\/56x56-000000-80-0-0.jpg","cover_medium":"https:\/\/e-cdns-images.dzcdn.net\/images\/cover\/2c420eb8b02e64ecb3f4cbaf8d340774\/250x250-000000-80-0-0.jpg","cover_big":"https:\/\/e-cdns-images.dzcdn.net\/images\/cover\/2c420eb8b02e64ecb3f4cbaf8d340774\/500x500-000000-80-0-0.jpg","cover_xl":"https:\/\/e-cdns-images.dzcdn.net\/images\/cover\/2c420eb8b02e64ecb3f4cbaf8d340774\/1000x1000-000000-80-0-0.jpg","md5_image":"2c420eb8b02e64ecb3f4cbaf8d340774","tracklist":"https:\/\/api.deezer.com\/album\/11344934\/tracks","type":"album"},"type":"track"},{"id":75517627,"readable":true,"title":"Miranda Y Mir\u00f3n (Single)","title_short":"Miranda Y Mir\u00f3n","title_version":"(Single)","link":"https:\/\/www.deezer.com\/track\/75517627","duration":147,"rank":329797,"explicit_lyrics":false,"explicit_content_lyrics":0,"explicit_content_cover":2,"preview":"https:\/\/cdns-preview-9.dzcdn.net\/stream\/c-958752433ac21c014e48d696cfddf490-5.mp3","md5_image":"6f9edb43e77a208e6e61cfb2b80175c9","artist":{"id":12452336,"name":"El Reino Infantil","link":"https:\/\/www.deezer.com\/artist\/12452336","picture":"https:\/\/api.deezer.com\/artist\/12452336\/image","picture_small":"https:\/\/e-cdns-images.dzcdn.net\/images\/artist\/15e27c692309434cc4e6152610b11610\/56x56-000000-80-0-0.jpg","picture_medium":"https:\/\/e-cdns-images.dzcdn.net\/images\/artist\/15e27c692309434cc4e6152610b11610\/250x250-000000-80-0-0.jpg","picture_big":"https:\/\/e-cdns-images.dzcdn.net\/images\/artist\/15e27c692309434cc4e6152610b11610\/500x500-000000-80-0-0.jpg","picture_xl":"https:\/\/e-cdns-images.dzcdn.net\/images\/artist\/15e27c692309434cc4e6152610b11610\/1000x1000-000000-80-0-0.jpg","tracklist":"https:\/\/api.deezer.com\/artist\/12452336\/top?limit=50","type":"artist"},"album":{"id":7479190,"title":"La Granja de Zen\u00f3n Vol. 2","cover":"https:\/\/api.deezer.com\/album\/7479190\/image","cover_small":"https:\/\/e-cdns-images.dzcdn.net\/images\/cover\/6f9edb43e77a208e6e61cfb2b80175c9\/56x56-000000-80-0-0.jpg","cover_medium":"https:\/\/e-cdns-images.dzcdn.net\/images\/cover\/6f9edb43e77a208e6e61cfb2b80175c9\/250x250-000000-80-0-0.jpg","cover_big":"https:\/\/e-cdns-images.dzcdn.net\/images\/cover\/6f9edb43e77a208e6e61cfb2b80175c9\/500x500-000000-80-0-0.jpg","cover_xl":"https:\/\/e-cdns-images.dzcdn.net\/images\/cover\/6f9edb43e77a208e6e61cfb2b80175c9\/1000x1000-000000-80-0-0.jpg","md5_image":"6f9edb43e77a208e6e61cfb2b80175c9","tracklist":"https:\/\/api.deezer.com\/album\/7479190\/tracks","type":"album"},"type":"track"},{"id":2046708507,"readable":true,"title":"Navidad","title_short":"Navidad","title_version":"","link":"https:\/\/www.deezer.com\/track\/2046708507","duration":194,"rank":369579,"explicit_lyrics":false,"explicit_content_lyrics":0,"explicit_content_cover":2,"preview":"https:\/\/cdns-preview-2.dzcdn.net\/stream\/c-2d54a6fdebfe77c55ad2405ed3ec20db-4.mp3","md5_image":"d917678338ff2602a5ee68a363908583","artist":{"id":4996,"name":"Miranda!","link":"https:\/\/www.deezer.com\/artist\/4996","picture":"https:\/\/api.deezer.com\/artist\/4996\/image","picture_small":"https:\/\/e-cdns-images.dzcdn.net\/images\/artist\/4e835792136fd35d7d442a79ec13e9fe\/56x56-000000-80-0-0.jpg","picture_medium":"https:\/\/e-cdns-images.dzcdn.net\/images\/artist\/4e835792136fd35d7d442a79ec13e9fe\/250x250-000000-80-0-0.jpg","picture_big":"https:\/\/e-cdns-images.dzcdn.net\/images\/artist\/4e835792136fd35d7d442a79ec13e9fe\/500x500-000000-80-0-0.jpg","picture_xl":"https:\/\/e-cdns-images.dzcdn.net\/images\/artist\/4e835792136fd35d7d442a79ec13e9fe\/1000x1000-000000-80-0-0.jpg","tracklist":"https:\/\/api.deezer.com\/artist\/4996\/top?limit=50","type":"artist"},"album":{"id":382645707,"title":"Navidad","cover":"https:\/\/api.deezer.com\/album\/382645707\/image","cover_small":"https:\/\/e-cdns-images.dzcdn.net\/images\/cover\/d917678338ff2602a5ee68a363908583\/56x56-000000-80-0-0.jpg","cover_medium":"https:\/\/e-cdns-images.dzcdn.net\/images\/cover\/d917678338ff2602a5ee68a363908583\/250x250-000000-80-0-0.jpg","cover_big":"https:\/\/e-cdns-images.dzcdn.net\/images\/cover\/d917678338ff2602a5ee68a363908583\/500x500-000000-80-0-0.jpg","cover_xl":"https:\/\/e-cdns-images.dzcdn.net\/images\/cover\/d917678338ff2602a5ee68a363908583\/1000x1000-000000-80-0-0.jpg","md5_image":"d917678338ff2602a5ee68a363908583","tracklist":"https:\/\/api.deezer.com\/album\/382645707\/tracks","type":"album"},"type":"track"},{"id":347292151,"readable":true,"title":"743","title_short":"743","title_version":"","link":"https:\/\/www.deezer.com\/track\/347292151","duration":206,"rank":328357,"explicit_lyrics":false,"explicit_content_lyrics":0,"explicit_content_cover":2,"preview":"https:\/\/cdns-preview-8.dzcdn.net\/stream\/c-828e7cfef10289c5cc48b5cdb023436d-3.mp3","md5_image":"a2e4b2be23ee0eb34b0266fa32d4ab37","artist":{"id":4996,"name":"Miranda!","link":"https:\/\/www.deezer.com\/artist\/4996","picture":"https:\/\/api.deezer.com\/artist\/4996\/image","picture_small":"https:\/\/e-cdns-images.dzcdn.net\/images\/artist\/4e835792136fd35d7d442a79ec13e9fe\/56x56-000000-80-0-0.jpg","picture_medium":"https:\/\/e-cdns-images.dzcdn.net\/images\/artist\/4e835792136fd35d7d442a79ec13e9fe\/250x250-000000-80-0-0.jpg","picture_big":"https:\/\/e-cdns-images.dzcdn.net\/images\/artist\/4e835792136fd35d7d442a79ec13e9fe\/500x500-000000-80-0-0.jpg","picture_xl":"https:\/\/e-cdns-images.dzcdn.net\/images\/artist\/4e835792136fd35d7d442a79ec13e9fe\/1000x1000-000000-80-0-0.jpg","tracklist":"https:\/\/api.deezer.com\/artist\/4996\/top?limit=50","type":"artist"},"album":{"id":39549621,"title":"Fuerte","cover":"https:\/\/api.deezer.com\/album\/39549621\/image","cover_small":"https:\/\/e-cdns-images.dzcdn.net\/images\/cover\/a2e4b2be23ee0eb34b0266fa32d4ab37\/56x56-000000-80-0-0.jpg","cover_medium":"https:\/\/e-cdns-images.dzcdn.net\/images\/cover\/a2e4b2be23ee0eb34b0266fa32d4ab37\/250x250-000000-80-0-0.jpg","cover_big":"https:\/\/e-cdns-images.dzcdn.net\/images\/cover\/a2e4b2be23ee0eb34b0266fa32d4ab37\/500x500-000000-80-0-0.jpg","cover_xl":"https:\/\/e-cdns-images.dzcdn.net\/images\/cover\/a2e4b2be23ee0eb34b0266fa32d4ab37\/1000x1000-000000-80-0-0.jpg","md5_image":"a2e4b2be23ee0eb34b0266fa32d4ab37","tracklist":"https:\/\/api.deezer.com\/album\/39549621\/tracks","type":"album"},"type":"track"},{"id":109383944,"readable":true,"title":"Lo Que Siento por Ti","title_short":"Lo Que Siento por Ti","link":"https:\/\/www.deezer.com\/track\/109383944","duration":192,"rank":290830,"explicit_lyrics":true,"explicit_content_lyrics":1,"explicit_content_cover":2,"preview":"https:\/\/cdns-preview-c.dzcdn.net\/stream\/c-c5a490ff43b72c25ad21ad97a182b9d9-7.mp3","md5_image":"d9b9fb4f9336acdceb807f0a736fdeb1","artist":{"id":4996,"name":"Miranda!","link":"https:\/\/www.deezer.com\/artist\/4996","picture":"https:\/\/api.deezer.com\/artist\/4996\/image","picture_small":"https:\/\/e-cdns-images.dzcdn.net\/images\/artist\/4e835792136fd35d7d442a79ec13e9fe\/56x56-000000-80-0-0.jpg","picture_medium":"https:\/\/e-cdns-images.dzcdn.net\/images\/artist\/4e835792136fd35d7d442a79ec13e9fe\/250x250-000000-80-0-0.jpg","picture_big":"https:\/\/e-cdns-images.dzcdn.net\/images\/artist\/4e835792136fd35d7d442a79ec13e9fe\/500x500-000000-80-0-0.jpg","picture_xl":"https:\/\/e-cdns-images.dzcdn.net\/images\/artist\/4e835792136fd35d7d442a79ec13e9fe\/1000x1000-000000-80-0-0.jpg","tracklist":"https:\/\/api.deezer.com\/artist\/4996\/top?limit=50","type":"artist"},"album":{"id":11396462,"title":"Miranda Es Imposible!","cover":"https:\/\/api.deezer.com\/album\/11396462\/image","cover_small":"https:\/\/e-cdns-images.dzcdn.net\/images\/cover\/d9b9fb4f9336acdceb807f0a736fdeb1\/56x56-000000-80-0-0.jpg","cover_medium":"https:\/\/e-cdns-images.dzcdn.net\/images\/cover\/d9b9fb4f9336acdceb807f0a736fdeb1\/250x250-000000-80-0-0.jpg","cover_big":"https:\/\/e-cdns-images.dzcdn.net\/images\/cover\/d9b9fb4f9336acdceb807f0a736fdeb1\/500x500-000000-80-0-0.jpg","cover_xl":"https:\/\/e-cdns-images.dzcdn.net\/images\/cover\/d9b9fb4f9336acdceb807f0a736fdeb1\/1000x1000-000000-80-0-0.jpg","md5_image":"d9b9fb4f9336acdceb807f0a736fdeb1","tracklist":"https:\/\/api.deezer.com\/album\/11396462\/tracks","type":"album"},"type":"track"},{"id":1765230417,"readable":true,"title":"Lo sab\u00eda","title_short":"Lo sab\u00eda","title_version":"","link":"https:\/\/www.deezer.com\/track\/1765230417","duration":199,"rank":318857,"explicit_lyrics":false,"explicit_content_lyrics":6,"explicit_content_cover":2,"preview":"https:\/\/cdns-preview-3.dzcdn.net\/stream\/c-3e50a589b5473d9b1d67f68ad1d80f82-3.mp3","md5_image":"193dae73f51782e040a39dfb88fca5ec","artist":{"id":314830,"name":"Babi","link":"https:\/\/www.deezer.com\/artist\/314830","picture":"https:\/\/api.deezer.com\/artist\/314830\/image","picture_small":"https:\/\/e-cdns-images.dzcdn.net\/images\/artist\/44981bc7053868b60d92a6a1bced6baa\/56x56-000000-80-0-0.jpg","picture_medium":"https:\/\/e-cdns-images.dzcdn.net\/images\/artist\/44981bc7053868b60d92a6a1bced6baa\/250x250-000000-80-0-0.jpg","picture_big":"https:\/\/e-cdns-images.dzcdn.net\/images\/artist\/44981bc7053868b60d92a6a1bced6baa\/500x500-000000-80-0-0.jpg","picture_xl":"https:\/\/e-cdns-images.dzcdn.net\/images\/artist\/44981bc7053868b60d92a6a1bced6baa\/1000x1000-000000-80-0-0.jpg","tracklist":"https:\/\/api.deezer.com\/artist\/314830\/top?limit=50","type":"artist"},"album":{"id":321648647,"title":"Lo sab\u00eda","cover":"https:\/\/api.deezer.com\/album\/321648647\/image","cover_small":"https:\/\/e-cdns-images.dzcdn.net\/images\/cover\/193dae73f51782e040a39dfb88fca5ec\/56x56-000000-80-0-0.jpg","cover_medium":"https:\/\/e-cdns-images.dzcdn.net\/images\/cover\/193dae73f51782e040a39dfb88fca5ec\/250x250-000000-80-0-0.jpg","cover_big":"https:\/\/e-cdns-images.dzcdn.net\/images\/cover\/193dae73f51782e040a39dfb88fca5ec\/500x500-000000-80-0-0.jpg","cover_xl":"https:\/\/e-cdns-images.dzcdn.net\/images\/cover\/193dae73f51782e040a39dfb88fca5ec\/1000x1000-000000-80-0-0.jpg","md5_image":"193dae73f51782e040a39dfb88fca5ec","tracklist":"https:\/\/api.deezer.com\/album\/321648647\/tracks","type":"album"},"type":"track"},{"id":938895642,"readable":true,"title":"Casi Feliz","title_short":"Casi Feliz","title_version":"","link":"https:\/\/www.deezer.com\/track\/938895642","duration":165,"rank":262405,"explicit_lyrics":false,"explicit_content_lyrics":0,"explicit_content_cover":2,"preview":"https:\/\/cdns-preview-3.dzcdn.net\/stream\/c-34fd3b974a0cb14191e3f38377cc4452-5.mp3","md5_image":"97ad515554c83c50c0cd4db0ca4aa520","artist":{"id":4996,"name":"Miranda!","link":"https:\/\/www.deezer.com\/artist\/4996","picture":"https:\/\/api.deezer.com\/artist\/4996\/image","picture_small":"https:\/\/e-cdns-images.dzcdn.net\/images\/artist\/4e835792136fd35d7d442a79ec13e9fe\/56x56-000000-80-0-0.jpg","picture_medium":"https:\/\/e-cdns-images.dzcdn.net\/images\/artist\/4e835792136fd35d7d442a79ec13e9fe\/250x250-000000-80-0-0.jpg","picture_big":"https:\/\/e-cdns-images.dzcdn.net\/images\/artist\/4e835792136fd35d7d442a79ec13e9fe\/500x500-000000-80-0-0.jpg","picture_xl":"https:\/\/e-cdns-images.dzcdn.net\/images\/artist\/4e835792136fd35d7d442a79ec13e9fe\/1000x1000-000000-80-0-0.jpg","tracklist":"https:\/\/api.deezer.com\/artist\/4996\/top?limit=50","type":"artist"},"album":{"id":143798582,"title":"Casi Feliz","cover":"https:\/\/api.deezer.com\/album\/143798582\/image","cover_small":"https:\/\/e-cdns-images.dzcdn.net\/images\/cover\/97ad515554c83c50c0cd4db0ca4aa520\/56x56-000000-80-0-0.jpg","cover_medium":"https:\/\/e-cdns-images.dzcdn.net\/images\/cover\/97ad515554c83c50c0cd4db0ca4aa520\/250x250-000000-80-0-0.jpg","cover_big":"https:\/\/e-cdns-images.dzcdn.net\/images\/cover\/97ad515554c83c50c0cd4db0ca4aa520\/500x500-000000-80-0-0.jpg","cover_xl":"https:\/\/e-cdns-images.dzcdn.net\/images\/cover\/97ad515554c83c50c0cd4db0ca4aa520\/1000x1000-000000-80-0-0.jpg","md5_image":"97ad515554c83c50c0cd4db0ca4aa520","tracklist":"https:\/\/api.deezer.com\/album\/143798582\/tracks","type":"album"},"type":"track"},{"id":108828802,"readable":true,"title":"Fantasmas","title_short":"Fantasmas","title_version":"","link":"https:\/\/www.deezer.com\/track\/108828802","duration":214,"rank":306840,"explicit_lyrics":false,"explicit_content_lyrics":0,"explicit_content_cover":2,"preview":"https:\/\/cdns-preview-7.dzcdn.net\/stream\/c-76e6d15abab593a589a25d552eae27df-5.mp3","md5_image":"2c420eb8b02e64ecb3f4cbaf8d340774","artist":{"id":4996,"name":"Miranda!","link":"https:\/\/www.deezer.com\/artist\/4996","picture":"https:\/\/api.deezer.com\/artist\/4996\/image","picture_small":"https:\/\/e-cdns-images.dzcdn.net\/images\/artist\/4e835792136fd35d7d442a79ec13e9fe\/56x56-000000-80-0-0.jpg","picture_medium":"https:\/\/e-cdns-images.dzcdn.net\/images\/artist\/4e835792136fd35d7d442a79ec13e9fe\/250x250-000000-80-0-0.jpg","picture_big":"https:\/\/e-cdns-images.dzcdn.net\/images\/artist\/4e835792136fd35d7d442a79ec13e9fe\/500x500-000000-80-0-0.jpg","picture_xl":"https:\/\/e-cdns-images.dzcdn.net\/images\/artist\/4e835792136fd35d7d442a79ec13e9fe\/1000x1000-000000-80-0-0.jpg","tracklist":"https:\/\/api.deezer.com\/artist\/4996\/top?limit=50","type":"artist"},"album":{"id":11344934,"title":"Safari","cover":"https:\/\/api.deezer.com\/album\/11344934\/image","cover_small":"https:\/\/e-cdns-images.dzcdn.net\/images\/cover\/2c420eb8b02e64ecb3f4cbaf8d340774\/56x56-000000-80-0-0.jpg","cover_medium":"https:\/\/e-cdns-images.dzcdn.net\/images\/cover\/2c420eb8b02e64ecb3f4cbaf8d340774\/250x250-000000-80-0-0.jpg","cover_big":"https:\/\/e-cdns-images.dzcdn.net\/images\/cover\/2c420eb8b02e64ecb3f4cbaf8d340774\/500x500-000000-80-0-0.jpg","cover_xl":"https:\/\/e-cdns-images.dzcdn.net\/images\/cover\/2c420eb8b02e64ecb3f4cbaf8d340774\/1000x1000-000000-80-0-0.jpg","md5_image":"2c420eb8b02e64ecb3f4cbaf8d340774","tracklist":"https:\/\/api.deezer.com\/album\/11344934\/tracks","type":"album"},"type":"track"},{"id":1366628092,"readable":true,"title":"Ca\u00eda la Noche","title_short":"Ca\u00eda la Noche","title_version":"","link":"https:\/\/www.deezer.com\/track\/1366628092","duration":191,"rank":317839,"explicit_lyrics":false,"explicit_content_lyrics":0,"explicit_content_cover":2,"preview":"https:\/\/cdns-preview-2.dzcdn.net\/stream\/c-24163b4cd6a6043ccd2c96f141673e67-4.mp3","md5_image":"dff901b5d6a624b9e519f50bd946fac9","artist":{"id":4996,"name":"Miranda!","link":"https:\/\/www.deezer.com\/artist\/4996","picture":"https:\/\/api.deezer.com\/artist\/4996\/image","picture_small":"https:\/\/e-cdns-images.dzcdn.net\/images\/artist\/4e835792136fd35d7d442a79ec13e9fe\/56x56-000000-80-0-0.jpg","picture_medium":"https:\/\/e-cdns-images.dzcdn.net\/images\/artist\/4e835792136fd35d7d442a79ec13e9fe\/250x250-000000-80-0-0.jpg","picture_big":"https:\/\/e-cdns-images.dzcdn.net\/images\/artist\/4e835792136fd35d7d442a79ec13e9fe\/500x500-000000-80-0-0.jpg","picture_xl":"https:\/\/e-cdns-images.dzcdn.net\/images\/artist\/4e835792136fd35d7d442a79ec13e9fe\/1000x1000-000000-80-0-0.jpg","tracklist":"https:\/\/api.deezer.com\/artist\/4996\/top?limit=50","type":"artist"},"album":{"id":228650912,"title":"Souvenir","cover":"https:\/\/api.deezer.com\/album\/228650912\/image","cover_small":"https:\/\/e-cdns-images.dzcdn.net\/images\/cover\/dff901b5d6a624b9e519f50bd946fac9\/56x56-000000-80-0-0.jpg","cover_medium":"https:\/\/e-cdns-images.dzcdn.net\/images\/cover\/dff901b5d6a624b9e519f50bd946fac9\/250x250-000000-80-0-0.jpg","cover_big":"https:\/\/e-cdns-images.dzcdn.net\/images\/cover\/dff901b5d6a624b9e519f50bd946fac9\/500x500-000000-80-0-0.jpg","cover_xl":"https:\/\/e-cdns-images.dzcdn.net\/images\/cover\/dff901b5d6a624b9e519f50bd946fac9\/1000x1000-000000-80-0-0.jpg","md5_image":"dff901b5d6a624b9e519f50bd946fac9","tracklist":"https:\/\/api.deezer.com\/album\/228650912\/tracks","type":"album"},"type":"track"},{"id":108828816,"readable":true,"title":"Nadie Como T\u00fa","title_short":"Nadie Como T\u00fa","title_version":"","link":"https:\/\/www.deezer.com\/track\/108828816","duration":205,"rank":315746,"explicit_lyrics":false,"explicit_content_lyrics":0,"explicit_content_cover":2,"preview":"https:\/\/cdns-preview-a.dzcdn.net\/stream\/c-a0b03f4a0eaea104cb25cdfc04262b72-5.mp3","md5_image":"2c420eb8b02e64ecb3f4cbaf8d340774","artist":{"id":4996,"name":"Miranda!","link":"https:\/\/www.deezer.com\/artist\/4996","picture":"https:\/\/api.deezer.com\/artist\/4996\/image","picture_small":"https:\/\/e-cdns-images.dzcdn.net\/images\/artist\/4e835792136fd35d7d442a79ec13e9fe\/56x56-000000-80-0-0.jpg","picture_medium":"https:\/\/e-cdns-images.dzcdn.net\/images\/artist\/4e835792136fd35d7d442a79ec13e9fe\/250x250-000000-80-0-0.jpg","picture_big":"https:\/\/e-cdns-images.dzcdn.net\/images\/artist\/4e835792136fd35d7d442a79ec13e9fe\/500x500-000000-80-0-0.jpg","picture_xl":"https:\/\/e-cdns-images.dzcdn.net\/images\/artist\/4e835792136fd35d7d442a79ec13e9fe\/1000x1000-000000-80-0-0.jpg","tracklist":"https:\/\/api.deezer.com\/artist\/4996\/top?limit=50","type":"artist"},"album":{"id":11344934,"title":"Safari","cover":"https:\/\/api.deezer.com\/album\/11344934\/image","cover_small":"https:\/\/e-cdns-images.dzcdn.net\/images\/cover\/2c420eb8b02e64ecb3f4cbaf8d340774\/56x56-000000-80-0-0.jpg","cover_medium":"https:\/\/e-cdns-images.dzcdn.net\/images\/cover\/2c420eb8b02e64ecb3f4cbaf8d340774\/250x250-000000-80-0-0.jpg","cover_big":"https:\/\/e-cdns-images.dzcdn.net\/images\/cover\/2c420eb8b02e64ecb3f4cbaf8d340774\/500x500-000000-80-0-0.jpg","cover_xl":"https:\/\/e-cdns-images.dzcdn.net\/images\/cover\/2c420eb8b02e64ecb3f4cbaf8d340774\/1000x1000-000000-80-0-0.jpg","md5_image":"2c420eb8b02e64ecb3f4cbaf8d340774","tracklist":"https:\/\/api.deezer.com\/album\/11344934\/tracks","type":"album"},"type":"track"}],"total":300,"next":"https:\/\/api.deezer.com\/search?q=miranda&index=25"}