{"id":46,"name":"Christine Milton","link":"https:\/\/www.deezer.com\/artist\/46","share":"https:\/\/www.deezer.com\/artist\/46?utm_source=deezer&utm_content=artist-46&utm_term=0_1672294459&utm_medium=web","picture":"https:\/\/api.deezer.com\/artist\/46\/image","picture_small":"https:\/\/e-cdns-images.dzcdn.net\/images\/artist\/09bc4d01320143e6dd3ecc3026106c87\/56x56-000000-80-0-0.jpg","picture_medium":"https:\/\/e-cdns-images.dzcdn.net\/images\/artist\/09bc4d01320143e6dd3ecc3026106c87\/250x250-000000-80-0-0.jpg","picture_big":"https:\/\/e-cdns-images.dzcdn.net\/images\/artist\/09bc4d01320143e6dd3ecc3026106c87\/500x500-000000-80-0-0.jpg","picture_xl":"https:\/\/e-cdns-images.dzcdn.net\/images\/artist\/09bc4d01320143e6dd3ecc3026106c87\/1000x1000-000000-80-0-0.jpg","nb_album":5,"nb_fan":71,"radio":true,"tracklist":"https:\/\/api.deezer.com\/artist\/46\/top?limit=50","type":"artist"}